doqs/__init__.py
doqs-0.0.0.dist-info/LICENSE
doqs-0.0.0.dist-info/WHEEL
doqs-0.0.0.dist-info/METADATA
doqs-0.0.0.dist-info/RECORD
