Metadata-Version: 2.1
Name: doqs
Version: 0.0.0
Summary: Official python SDK for doqs.dev
Author-email: "doqs.dev" <support@doqs.dev>
Classifier: License :: OSI Approved :: MIT License
Project-URL: Home, https://doqs.dev
